setup.py
piped.contrib.amqp.egg-info/PKG-INFO
piped.contrib.amqp.egg-info/SOURCES.txt
piped.contrib.amqp.egg-info/dependency_links.txt
piped.contrib.amqp.egg-info/requires.txt
piped.contrib.amqp.egg-info/top_level.txt
piped/plugins/amqp_providers.py
piped_amqp/__init__.py
piped_amqp/providers.py
piped_amqp/rpc.py
piped_amqp/test/__init__.py
piped_amqp/test/test_providers.py
piped_amqp/test/test_rpc.py