Metadata-Version: 1.0
Name: piped.contrib.amqp
Version: 0.4.0
Summary: AMQP support for Piped.
Home-page: http://piped.io
Author: Piped Project Contributors
Author-email: piped@librelist.com
License: MIT
Platform: UNKNOWN
Classifier: Development Status :: 4 - Beta
Classifier: Environment :: Plugins
Classifier: Framework :: Twisted
Classifier: Operating System :: OS Independent
